examples/cop30dem/example_cop30dem.py
examples/hlsmpc/example_hlsmpc.py
examples/landsatmpc/example_landsatmpc.py
examples/s1mpc/example_s1mpc.py
examples/s2e84/example_s2e84.py
examples/s2mpc/example_s2mpc.py
sat_data_acquisition/__init__.py
sat_data_acquisition/__version__.py
sat_data_acquisition/config/__init__.py
sat_data_acquisition/config/logging.py
sat_data_acquisition/config/settings.py
sat_data_acquisition/core/__init__.py
sat_data_acquisition/core/base_iterator.py
sat_data_acquisition/core/stac_client.py
sat_data_acquisition/models/__init__.py
sat_data_acquisition/models/params.py
sat_data_acquisition/processing/__init__.py
sat_data_acquisition/processing/core.py
sat_data_acquisition/processing/save.py
sat_data_acquisition/processing/utils.py
sat_data_acquisition/providers/__init__.py
sat_data_acquisition/providers/element84.py
sat_data_acquisition/providers/mpc.py
sat_data_acquisition/utils/__init__.py
sat_data_acquisition/utils/coordinate_converter.py
sat_data_acquisition/utils/exceptions.py
sat_data_acquisition-0.9.0.dist-info/licenses/LICENSE
tests/conftest.py
tests/test_config.py
tests/test_integration.py
tests/test_params.py
tests/test_processing.py
tests/test_products.py
tests/test_utils.py
sat_data_acquisition-0.9.0.dist-info/METADATA
sat_data_acquisition-0.9.0.dist-info/WHEEL
sat_data_acquisition-0.9.0.dist-info/top_level.txt
sat_data_acquisition-0.9.0.dist-info/RECORD
