Metadata-Version: 2.4
Name: sat_data_acquisition
Version: 0.9.0
Summary: Lightweight satellite data retrieval from public STAC sources
Author: Peter Kongstad
License: MIT
Project-URL: Homepage, https://github.com/Kongstad/sat-data-acquisition
Project-URL: Repository, https://github.com/Kongstad/sat-data-acquisition
Project-URL: Documentation, https://github.com/Kongstad/sat-data-acquisition#readme
Keywords: satellite,imagery,raster,STAC,Sentinel,Landsat,geospatial
Classifier: Development Status :: 3 - Alpha
Classifier: Intended Audience :: Science/Research
Classifier: License :: OSI Approved :: MIT License
Classifier: Programming Language :: Python :: 3
Classifier: Programming Language :: Python :: 3.12
Classifier: Programming Language :: Python :: 3.13
Classifier: Topic :: Scientific/Engineering :: GIS
Requires-Python: >=3.12
License-File: LICENSE
Requires-Dist: geopandas>=0.13.0
Requires-Dist: rasterio>=1.3.0
Requires-Dist: xarray>=2023.1.0
Requires-Dist: odc-stac>=0.3.0
Requires-Dist: pystac-client>=0.6.0
Requires-Dist: planetary-computer>=0.4.9
Requires-Dist: rioxarray>=0.14.0
Requires-Dist: shapely>=2.0.0
Requires-Dist: numpy>=1.24.0
Requires-Dist: pandas>=2.0.0
Requires-Dist: pyproj>=3.4.0
Requires-Dist: utm>=0.7.0
Requires-Dist: pydantic>=2.0.0
Requires-Dist: pydantic-settings>=2.0.0
Requires-Dist: python-dotenv>=1.0.0
Requires-Dist: boto3>=1.28.0
Requires-Dist: tqdm>=4.65.0
Requires-Dist: matplotlib>=3.7.0
Requires-Dist: pytest-cov>=4.0.0
Dynamic: license-file
